[
  {
    "ATPT_OFCDC_SC_CODE": "T10",
    "ATPT_OFCDC_SC_NM": "제주특별자치도교육청",
    "SD_SCHUL_CODE": "9299048",
    "SCHUL_NM": "가마초등학교"
  },
  {
    "ATPT_OFCDC_SC_CODE": "T10",
    "ATPT_OFCDC_SC_NM": "제주특별자치도교육청",
    "SD_SCHUL_CODE": "9299061",
    "SCHUL_NM": "가파초등학교"
  },
  {
    "ATPT_OFCDC_SC_CODE": "T10",
    "ATPT_OFCDC_SC_NM": "제주특별자치도교육청",
    "SD_SCHUL_CODE": "9299070",
    "SCHUL_NM": "가파초등학교마라분교장"
  },
  {
    "ATPT_OFCDC_SC_CODE": "T10",
    "ATPT_OFCDC_SC_NM": "제주특별자치도교육청",
    "SD_SCHUL_CODE": "9299037",
    "SCHUL_NM": "강정초등학교"
  },
  {
    "ATPT_OFCDC_SC_CODE": "T10",
    "ATPT_OFCDC_SC_NM": "제주특별자치도교육청",
    "SD_SCHUL_CODE": "9296023",
    "SCHUL_NM": "고산중학교"
  },
  {
    "ATPT_OFCDC_SC_CODE": "T10",
    "ATPT_OFCDC_SC_NM": "제주특별자치도교육청",
    "SD_SCHUL_CODE": "9296079",
    "SCHUL_NM": "고산초등학교"
  },
  {
    "ATPT_OFCDC_SC_CODE": "T10",
    "ATPT_OFCDC_SC_NM": "제주특별자치도교육청",
    "SD_SCHUL_CODE": "9296072",
    "SCHUL_NM": "곽금초등학교"
  },
  {
    "ATPT_OFCDC_SC_CODE": "T10",
    "ATPT_OFCDC_SC_NM": "제주특별자치도교육청",
    "SD_SCHUL_CODE": "9296067",
    "SCHUL_NM": "광령초등학교"
  },
  {
    "ATPT_OFCDC_SC_CODE": "T10",
    "ATPT_OFCDC_SC_NM": "제주특별자치도교육청",
    "SD_SCHUL_CODE": "9296042",
    "SCHUL_NM": "광양초등학교"
  },
  {
    "ATPT_OFCDC_SC_CODE": "T10",
    "ATPT_OFCDC_SC_NM": "제주특별자치도교육청",
    "SD_SCHUL_CODE": "9296069",
    "SCHUL_NM": "구엄초등학교"
  },
  {
    "ATPT_OFCDC_SC_CODE": "T10",
    "ATPT_OFCDC_SC_NM": "제주특별자치도교육청",
    "SD_SCHUL_CODE": "9296088",
    "SCHUL_NM": "구좌중앙초등학교"
  },
  {
    "ATPT_OFCDC_SC_CODE": "T10",
    "ATPT_OFCDC_SC_NM": "제주특별자치도교육청",
    "SD_SCHUL_CODE": "9296074",
    "SCHUL_NM": "귀덕초등학교"
  },
  {
    "ATPT_OFCDC_SC_CODE": "T10",
    "ATPT_OFCDC_SC_NM": "제주특별자치도교육청",
    "SD_SCHUL_CODE": "9296036",
    "SCHUL_NM": "귀일중학교"
  },
  {
    "ATPT_OFCDC_SC_CODE": "T10",
    "ATPT_OFCDC_SC_NM": "제주특별자치도교육청",
    "SD_SCHUL_CODE": "9296078",
    "SCHUL_NM": "금악초등학교"
  },
  {
    "ATPT_OFCDC_SC_CODE": "T10",
    "ATPT_OFCDC_SC_NM": "제주특별자치도교육청",
    "SD_SCHUL_CODE": "9296028",
    "SCHUL_NM": "김녕중학교"
  },
  {
    "ATPT_OFCDC_SC_CODE": "T10",
    "ATPT_OFCDC_SC_NM": "제주특별자치도교육청",
    "SD_SCHUL_CODE": "9296087",
    "SCHUL_NM": "김녕초등학교"
  },
  {
    "ATPT_OFCDC_SC_CODE": "T10",
    "ATPT_OFCDC_SC_NM": "제주특별자치도교육청",
    "SD_SCHUL_CODE": "9296104",
    "SCHUL_NM": "김녕초등학교동복분교장"
  },
  {
    "ATPT_OFCDC_SC_CODE": "T10",
    "ATPT_OFCDC_SC_NM": "제주특별자치도교육청",
    "SD_SCHUL_CODE": "9296047",
    "SCHUL_NM": "남광초등학교"
  },
  {
    "ATPT_OFCDC_SC_CODE": "T10",
    "ATPT_OFCDC_SC_NM": "제주특별자치도교육청",
    "SD_SCHUL_CODE": "9290076",
    "SCHUL_NM": "남녕고등학교"
  },
  {
    "ATPT_OFCDC_SC_CODE": "T10",
    "ATPT_OFCDC_SC_NM": "제주특별자치도교육청",
    "SD_SCHUL_CODE": "9299017",
    "SCHUL_NM": "남원중학교"
  },
  {
    "ATPT_OFCDC_SC_CODE": "T10",
    "ATPT_OFCDC_SC_NM": "제주특별자치도교육청",
    "SD_SCHUL_CODE": "9299054",
    "SCHUL_NM": "남원초등학교"
  },
  {
    "ATPT_OFCDC_SC_CODE": "T10",
    "ATPT_OFCDC_SC_NM": "제주특별자치도교육청",
    "SD_SCHUL_CODE": "9290073",
    "SCHUL_NM": "남주고등학교"
  },
  {
    "ATPT_OFCDC_SC_CODE": "T10",
    "ATPT_OFCDC_SC_NM": "제주특별자치도교육청",
    "SD_SCHUL_CODE": "9299023",
    "SCHUL_NM": "남주중학교"
  },
  {
    "ATPT_OFCDC_SC_CODE": "T10",
    "ATPT_OFCDC_SC_NM": "제주특별자치도교육청",
    "SD_SCHUL_CODE": "9296070",
    "SCHUL_NM": "납읍초등학교"
  },
  {
    "ATPT_OFCDC_SC_CODE": "T10",
    "ATPT_OFCDC_SC_NM": "제주특별자치도교육청",
    "SD_SCHUL_CODE": "9296185",
    "SCHUL_NM": "노형중학교"
  },
  {
    "ATPT_OFCDC_SC_CODE": "T10",
    "ATPT_OFCDC_SC_NM": "제주특별자치도교육청",
    "SD_SCHUL_CODE": "9296056",
    "SCHUL_NM": "노형초등학교"
  },
  {
    "ATPT_OFCDC_SC_CODE": "T10",
    "ATPT_OFCDC_SC_NM": "제주특별자치도교육청",
    "SD_SCHUL_CODE": "9290075",
    "SCHUL_NM": "대기고등학교"
  },
  {
    "ATPT_OFCDC_SC_CODE": "T10",
    "ATPT_OFCDC_SC_NM": "제주특별자치도교육청",
    "SD_SCHUL_CODE": "9290056",
    "SCHUL_NM": "대정고등학교"
  },
  {
    "ATPT_OFCDC_SC_CODE": "T10",
    "ATPT_OFCDC_SC_NM": "제주특별자치도교육청",
    "SD_SCHUL_CODE": "9299058",
    "SCHUL_NM": "대정서초등학교"
  },
  {
    "ATPT_OFCDC_SC_CODE": "T10",
    "ATPT_OFCDC_SC_NM": "제주특별자치도교육청",
    "SD_SCHUL_CODE": "9290057",
    "SCHUL_NM": "대정여자고등학교"
  },
  {
    "ATPT_OFCDC_SC_CODE": "T10",
    "ATPT_OFCDC_SC_NM": "제주특별자치도교육청",
    "SD_SCHUL_CODE": "9299020",
    "SCHUL_NM": "대정중학교"
  },
  {
    "ATPT_OFCDC_SC_CODE": "T10",
    "ATPT_OFCDC_SC_NM": "제주특별자치도교육청",
    "SD_SCHUL_CODE": "9299059",
    "SCHUL_NM": "대정초등학교"
  },
  {
    "ATPT_OFCDC_SC_CODE": "T10",
    "ATPT_OFCDC_SC_NM": "제주특별자치도교육청",
    "SD_SCHUL_CODE": "9296084",
    "SCHUL_NM": "대흘초등학교"
  },
  {
    "ATPT_OFCDC_SC_CODE": "T10",
    "ATPT_OFCDC_SC_NM": "제주특별자치도교육청",
    "SD_SCHUL_CODE": "9296204",
    "SCHUL_NM": "더럭초등학교"
  },
  {
    "ATPT_OFCDC_SC_CODE": "T10",
    "ATPT_OFCDC_SC_NM": "제주특별자치도교육청",
    "SD_SCHUL_CODE": "9299063",
    "SCHUL_NM": "덕수초등학교"
  },
  {
    "ATPT_OFCDC_SC_CODE": "T10",
    "ATPT_OFCDC_SC_NM": "제주특별자치도교육청",
    "SD_SCHUL_CODE": "9296049",
    "SCHUL_NM": "도남초등학교"
  },
  {
    "ATPT_OFCDC_SC_CODE": "T10",
    "ATPT_OFCDC_SC_NM": "제주특별자치도교육청",
    "SD_SCHUL_CODE": "9296195",
    "SCHUL_NM": "도련초등학교"
  },
  {
    "ATPT_OFCDC_SC_CODE": "T10",
    "ATPT_OFCDC_SC_NM": "제주특별자치도교육청",
    "SD_SCHUL_CODE": "9296057",
    "SCHUL_NM": "도리초등학교"
  },
  {
    "ATPT_OFCDC_SC_CODE": "T10",
    "ATPT_OFCDC_SC_NM": "제주특별자치도교육청",
    "SD_SCHUL_CODE": "9299035",
    "SCHUL_NM": "도순초등학교"
  },
  {
    "ATPT_OFCDC_SC_CODE": "T10",
    "ATPT_OFCDC_SC_NM": "제주특별자치도교육청",
    "SD_SCHUL_CODE": "9296175",
    "SCHUL_NM": "도평초등학교"
  },
  {
    "ATPT_OFCDC_SC_CODE": "T10",
    "ATPT_OFCDC_SC_NM": "제주특별자치도교육청",
    "SD_SCHUL_CODE": "9296060",
    "SCHUL_NM": "동광초등학교"
  },
  {
    "ATPT_OFCDC_SC_CODE": "T10",
    "ATPT_OFCDC_SC_NM": "제주특별자치도교육청",
    "SD_SCHUL_CODE": "9299040",
    "SCHUL_NM": "동남초등학교"
  },
  {
    "ATPT_OFCDC_SC_CODE": "T10",
    "ATPT_OFCDC_SC_NM": "제주특별자치도교육청",
    "SD_SCHUL_CODE": "9299039",
    "SCHUL_NM": "동홍초등학교"
  },
  {
    "ATPT_OFCDC_SC_CODE": "T10",
    "ATPT_OFCDC_SC_NM": "제주특별자치도교육청",
    "SD_SCHUL_CODE": "9296061",
    "SCHUL_NM": "동화초등학교"
  },
  {
    "ATPT_OFCDC_SC_CODE": "T10",
    "ATPT_OFCDC_SC_NM": "제주특별자치도교육청",
    "SD_SCHUL_CODE": "9299021",
    "SCHUL_NM": "무릉중학교"
  },
  {
    "ATPT_OFCDC_SC_CODE": "T10",
    "ATPT_OFCDC_SC_NM": "제주특별자치도교육청",
    "SD_SCHUL_CODE": "9299067",
    "SCHUL_NM": "무릉초등학교"
  },
  {
    "ATPT_OFCDC_SC_CODE": "T10",
    "ATPT_OFCDC_SC_NM": "제주특별자치도교육청",
    "SD_SCHUL_CODE": "9296066",
    "SCHUL_NM": "물메초등학교"
  },
  {
    "ATPT_OFCDC_SC_CODE": "T10",
    "ATPT_OFCDC_SC_NM": "제주특별자치도교육청",
    "SD_SCHUL_CODE": "9296063",
    "SCHUL_NM": "백록초등학교"
  },
  {
    "ATPT_OFCDC_SC_CODE": "T10",
    "ATPT_OFCDC_SC_NM": "제주특별자치도교육청",
    "SD_SCHUL_CODE": "9299028",
    "SCHUL_NM": "법환초등학교"
  },
  {
    "ATPT_OFCDC_SC_CODE": "T10",
    "ATPT_OFCDC_SC_NM": "제주특별자치도교육청",
    "SD_SCHUL_CODE": "9299032",
    "SCHUL_NM": "보목초등학교"
  },
  {
    "ATPT_OFCDC_SC_CODE": "T10",
    "ATPT_OFCDC_SC_NM": "제주특별자치도교육청",
    "SD_SCHUL_CODE": "9299060",
    "SCHUL_NM": "보성초등학교"
  },
  {
    "ATPT_OFCDC_SC_CODE": "T10",
    "ATPT_OFCDC_SC_NM": "제주특별자치도교육청",
    "SD_SCHUL_CODE": "9296052",
    "SCHUL_NM": "봉개초등학교"
  },
  {
    "ATPT_OFCDC_SC_CODE": "T10",
    "ATPT_OFCDC_SC_NM": "제주특별자치도교육청",
    "SD_SCHUL_CODE": "9296086",
    "SCHUL_NM": "북촌초등학교"
  },
  {
    "ATPT_OFCDC_SC_CODE": "T10",
    "ATPT_OFCDC_SC_NM": "제주특별자치도교육청",
    "SD_SCHUL_CODE": "9299064",
    "SCHUL_NM": "사계초등학교"
  },
  {
    "ATPT_OFCDC_SC_CODE": "T10",
    "ATPT_OFCDC_SC_NM": "제주특별자치도교육청",
    "SD_SCHUL_CODE": "9290074",
    "SCHUL_NM": "삼성여자고등학교"
  },
  {
    "ATPT_OFCDC_SC_CODE": "T10",
    "ATPT_OFCDC_SC_NM": "제주특별자치도교육청",
    "SD_SCHUL_CODE": "9296045",
    "SCHUL_NM": "삼성초등학교"
  },
  {
    "ATPT_OFCDC_SC_CODE": "T10",
    "ATPT_OFCDC_SC_NM": "제주특별자치도교육청",
    "SD_SCHUL_CODE": "9296051",
    "SCHUL_NM": "삼양초등학교"
  },
  {
    "ATPT_OFCDC_SC_CODE": "T10",
    "ATPT_OFCDC_SC_NM": "제주특별자치도교육청",
    "SD_SCHUL_CODE": "9296192",
    "SCHUL_NM": "삼화초등학교"
  },
  {
    "ATPT_OFCDC_SC_CODE": "T10",
    "ATPT_OFCDC_SC_NM": "제주특별자치도교육청",
    "SD_SCHUL_CODE": "9299038",
    "SCHUL_NM": "새서귀초등학교"
  },
  {
    "ATPT_OFCDC_SC_CODE": "T10",
    "ATPT_OFCDC_SC_NM": "제주특별자치도교육청",
    "SD_SCHUL_CODE": "9299062",
    "SCHUL_NM": "서광초등학교"
  },
  {
    "ATPT_OFCDC_SC_CODE": "T10",
    "ATPT_OFCDC_SC_NM": "제주특별자치도교육청",
    "SD_SCHUL_CODE": "9299027",
    "SCHUL_NM": "서귀북초등학교"
  },
  {
    "ATPT_OFCDC_SC_CODE": "T10",
    "ATPT_OFCDC_SC_NM": "제주특별자치도교육청",
    "SD_SCHUL_CODE": "9299026",
    "SCHUL_NM": "서귀서초등학교"
  },
  {
    "ATPT_OFCDC_SC_CODE": "T10",
    "ATPT_OFCDC_SC_NM": "제주특별자치도교육청",
    "SD_SCHUL_CODE": "9299011",
    "SCHUL_NM": "서귀중앙여자중학교"
  },
  {
    "ATPT_OFCDC_SC_CODE": "T10",
    "ATPT_OFCDC_SC_NM": "제주특별자치도교육청",
    "SD_SCHUL_CODE": "9299025",
    "SCHUL_NM": "서귀중앙초등학교"
  },
  {
    "ATPT_OFCDC_SC_CODE": "T10",
    "ATPT_OFCDC_SC_NM": "제주특별자치도교육청",
    "SD_SCHUL_CODE": "9290059",
    "SCHUL_NM": "서귀포고등학교"
  },
  {
    "ATPT_OFCDC_SC_CODE": "T10",
    "ATPT_OFCDC_SC_NM": "제주특별자치도교육청",
    "SD_SCHUL_CODE": "9299014",
    "SCHUL_NM": "서귀포대신중학교"
  },
  {
    "ATPT_OFCDC_SC_CODE": "T10",
    "ATPT_OFCDC_SC_NM": "제주특별자치도교육청",
    "SD_SCHUL_CODE": "9290060",
    "SCHUL_NM": "서귀포산업과학고등학교"
  },
  {
    "ATPT_OFCDC_SC_CODE": "T10",
    "ATPT_OFCDC_SC_NM": "제주특별자치도교육청",
    "SD_SCHUL_CODE": "9290061",
    "SCHUL_NM": "서귀포여자고등학교"
  },
  {
    "ATPT_OFCDC_SC_CODE": "T10",
    "ATPT_OFCDC_SC_NM": "제주특별자치도교육청",
    "SD_SCHUL_CODE": "9299010",
    "SCHUL_NM": "서귀포여자중학교"
  },
  {
    "ATPT_OFCDC_SC_CODE": "T10",
    "ATPT_OFCDC_SC_NM": "제주특별자치도교육청",
    "SD_SCHUL_CODE": "9290085",
    "SCHUL_NM": "서귀포온성학교"
  },
  {
    "ATPT_OFCDC_SC_CODE": "T10",
    "ATPT_OFCDC_SC_NM": "제주특별자치도교육청",
    "SD_SCHUL_CODE": "9299009",
    "SCHUL_NM": "서귀포중학교"
  },
  {
    "ATPT_OFCDC_SC_CODE": "T10",
    "ATPT_OFCDC_SC_NM": "제주특별자치도교육청",
    "SD_SCHUL_CODE": "9299024",
    "SCHUL_NM": "서귀포초등학교"
  },
  {
    "ATPT_OFCDC_SC_CODE": "T10",
    "ATPT_OFCDC_SC_NM": "제주특별자치도교육청",
    "SD_SCHUL_CODE": "9299029",
    "SCHUL_NM": "서호초등학교"
  },
  {
    "ATPT_OFCDC_SC_CODE": "T10",
    "ATPT_OFCDC_SC_NM": "제주특별자치도교육청",
    "SD_SCHUL_CODE": "9296210",
    "SCHUL_NM": "선흘초등학교"
  },
  {
    "ATPT_OFCDC_SC_CODE": "T10",
    "ATPT_OFCDC_SC_NM": "제주특별자치도교육청",
    "SD_SCHUL_CODE": "9290102",
    "SCHUL_NM": "성산고등학교"
  },
  {
    "ATPT_OFCDC_SC_CODE": "T10",
    "ATPT_OFCDC_SC_NM": "제주특별자치도교육청",
    "SD_SCHUL_CODE": "9299015",
    "SCHUL_NM": "성산중학교"
  },
  {
    "ATPT_OFCDC_SC_CODE": "T10",
    "ATPT_OFCDC_SC_NM": "제주특별자치도교육청",
    "SD_SCHUL_CODE": "9299043",
    "SCHUL_NM": "성산초등학교"
  },
  {
    "ATPT_OFCDC_SC_CODE": "T10",
    "ATPT_OFCDC_SC_NM": "제주특별자치도교육청",
    "SD_SCHUL_CODE": "9299047",
    "SCHUL_NM": "성읍초등학교"
  },
  {
    "ATPT_OFCDC_SC_CODE": "T10",
    "ATPT_OFCDC_SC_NM": "제주특별자치도교육청",
    "SD_SCHUL_CODE": "9290064",
    "SCHUL_NM": "세화고등학교"
  },
  {
    "ATPT_OFCDC_SC_CODE": "T10",
    "ATPT_OFCDC_SC_NM": "제주특별자치도교육청",
    "SD_SCHUL_CODE": "9296029",
    "SCHUL_NM": "세화중학교"
  },
  {
    "ATPT_OFCDC_SC_CODE": "T10",
    "ATPT_OFCDC_SC_NM": "제주특별자치도교육청",
    "SD_SCHUL_CODE": "9296091",
    "SCHUL_NM": "세화초등학교"
  },
  {
    "ATPT_OFCDC_SC_CODE": "T10",
    "ATPT_OFCDC_SC_NM": "제주특별자치도교육청",
    "SD_SCHUL_CODE": "9296092",
    "SCHUL_NM": "송당초등학교"
  },
  {
    "ATPT_OFCDC_SC_CODE": "T10",
    "ATPT_OFCDC_SC_NM": "제주특별자치도교육청",
    "SD_SCHUL_CODE": "9299042",
    "SCHUL_NM": "수산초등학교"
  },
  {
    "ATPT_OFCDC_SC_CODE": "T10",
    "ATPT_OFCDC_SC_NM": "제주특별자치도교육청",
    "SD_SCHUL_CODE": "9296075",
    "SCHUL_NM": "수원초등학교"
  },
  {
    "ATPT_OFCDC_SC_CODE": "T10",
    "ATPT_OFCDC_SC_NM": "제주특별자치도교육청",
    "SD_SCHUL_CODE": "9299041",
    "SCHUL_NM": "시흥초등학교"
  },
  {
    "ATPT_OFCDC_SC_CODE": "T10",
    "ATPT_OFCDC_SC_NM": "제주특별자치도교육청",
    "SD_SCHUL_CODE": "9296059",
    "SCHUL_NM": "신광초등학교"
  },
  {
    "ATPT_OFCDC_SC_CODE": "T10",
    "ATPT_OFCDC_SC_NM": "제주특별자치도교육청",
    "SD_SCHUL_CODE": "9299056",
    "SCHUL_NM": "신례초등학교"
  },
  {
    "ATPT_OFCDC_SC_CODE": "T10",
    "ATPT_OFCDC_SC_NM": "제주특별자치도교육청",
    "SD_SCHUL_CODE": "9299022",
    "SCHUL_NM": "신산중학교"
  },
  {
    "ATPT_OFCDC_SC_CODE": "T10",
    "ATPT_OFCDC_SC_NM": "제주특별자치도교육청",
    "SD_SCHUL_CODE": "9299068",
    "SCHUL_NM": "신산초등학교"
  },
  {
    "ATPT_OFCDC_SC_CODE": "T10",
    "ATPT_OFCDC_SC_NM": "제주특별자치도교육청",
    "SD_SCHUL_CODE": "9290072",
    "SCHUL_NM": "신성여자고등학교"
  },
  {
    "ATPT_OFCDC_SC_CODE": "T10",
    "ATPT_OFCDC_SC_NM": "제주특별자치도교육청",
    "SD_SCHUL_CODE": "9296034",
    "SCHUL_NM": "신성여자중학교"
  },
  {
    "ATPT_OFCDC_SC_CODE": "T10",
    "ATPT_OFCDC_SC_NM": "제주특별자치도교육청",
    "SD_SCHUL_CODE": "9296019",
    "SCHUL_NM": "신엄중학교"
  },
  {
    "ATPT_OFCDC_SC_CODE": "T10",
    "ATPT_OFCDC_SC_NM": "제주특별자치도교육청",
    "SD_SCHUL_CODE": "9296044",
    "SCHUL_NM": "신제주초등학교"
  },
  {
    "ATPT_OFCDC_SC_CODE": "T10",
    "ATPT_OFCDC_SC_NM": "제주특별자치도교육청",
    "SD_SCHUL_CODE": "9296025",
    "SCHUL_NM": "신창중학교"
  },
  {
    "ATPT_OFCDC_SC_CODE": "T10",
    "ATPT_OFCDC_SC_NM": "제주특별자치도교육청",
    "SD_SCHUL_CODE": "9296081",
    "SCHUL_NM": "신창초등학교"
  },
  {
    "ATPT_OFCDC_SC_CODE": "T10",
    "ATPT_OFCDC_SC_NM": "제주특별자치도교육청",
    "SD_SCHUL_CODE": "9296082",
    "SCHUL_NM": "신촌초등학교"
  },
  {
    "ATPT_OFCDC_SC_CODE": "T10",
    "ATPT_OFCDC_SC_NM": "제주특별자치도교육청",
    "SD_SCHUL_CODE": "9296017",
    "SCHUL_NM": "아라중학교"
  },
  {
    "ATPT_OFCDC_SC_CODE": "T10",
    "ATPT_OFCDC_SC_NM": "제주특별자치도교육청",
    "SD_SCHUL_CODE": "9296053",
    "SCHUL_NM": "아라초등학교"
  },
  {
    "ATPT_OFCDC_SC_CODE": "T10",
    "ATPT_OFCDC_SC_NM": "제주특별자치도교육청",
    "SD_SCHUL_CODE": "9299019",
    "SCHUL_NM": "안덕중학교"
  },
  {
    "ATPT_OFCDC_SC_CODE": "T10",
    "ATPT_OFCDC_SC_NM": "제주특별자치도교육청",
    "SD_SCHUL_CODE": "9299065",
    "SCHUL_NM": "안덕초등학교"
  },
  {
    "ATPT_OFCDC_SC_CODE": "T10",
    "ATPT_OFCDC_SC_NM": "제주특별자치도교육청",
    "SD_SCHUL_CODE": "9290086",
    "SCHUL_NM": "애월고등학교"
  },
  {
    "ATPT_OFCDC_SC_CODE": "T10",
    "ATPT_OFCDC_SC_NM": "제주특별자치도교육청",
    "SD_SCHUL_CODE": "9296020",
    "SCHUL_NM": "애월중학교"
  },
  {
    "ATPT_OFCDC_SC_CODE": "T10",
    "ATPT_OFCDC_SC_NM": "제주특별자치도교육청",
    "SD_SCHUL_CODE": "9296071",
    "SCHUL_NM": "애월초등학교"
  },
  {
    "ATPT_OFCDC_SC_CODE": "T10",
    "ATPT_OFCDC_SC_NM": "제주특별자치도교육청",
    "SD_SCHUL_CODE": "9296073",
    "SCHUL_NM": "어도초등학교"
  },
  {
    "ATPT_OFCDC_SC_CODE": "T10",
    "ATPT_OFCDC_SC_NM": "제주특별자치도교육청",
    "SD_SCHUL_CODE": "9290089",
    "SCHUL_NM": "영주고등학교"
  },
  {
    "ATPT_OFCDC_SC_CODE": "T10",
    "ATPT_OFCDC_SC_NM": "제주특별자치도교육청",
    "SD_SCHUL_CODE": "9296054",
    "SCHUL_NM": "영평초등학교"
  },
  {
    "ATPT_OFCDC_SC_CODE": "T10",
    "ATPT_OFCDC_SC_NM": "제주특별자치도교육청",
    "SD_SCHUL_CODE": "9299034",
    "SCHUL_NM": "예래초등학교"
  },
  {
    "ATPT_OFCDC_SC_CODE": "T10",
    "ATPT_OFCDC_SC_NM": "제주특별자치도교육청",
    "SD_SCHUL_CODE": "9296055",
    "SCHUL_NM": "오라초등학교"
  },
  {
    "ATPT_OFCDC_SC_CODE": "T10",
    "ATPT_OFCDC_SC_NM": "제주특별자치도교육청",
    "SD_SCHUL_CODE": "9296197",
    "SCHUL_NM": "오름중학교"
  },
  {
    "ATPT_OFCDC_SC_CODE": "T10",
    "ATPT_OFCDC_SC_NM": "제주특별자치도교육청",
    "SD_SCHUL_CODE": "9290069",
    "SCHUL_NM": "오현고등학교"
  },
  {
    "ATPT_OFCDC_SC_CODE": "T10",
    "ATPT_OFCDC_SC_NM": "제주특별자치도교육청",
    "SD_SCHUL_CODE": "9296032",
    "SCHUL_NM": "오현중학교"
  },
  {
    "ATPT_OFCDC_SC_CODE": "T10",
    "ATPT_OFCDC_SC_NM": "제주특별자치도교육청",
    "SD_SCHUL_CODE": "9299044",
    "SCHUL_NM": "온평초등학교"
  },
  {
    "ATPT_OFCDC_SC_CODE": "T10",
    "ATPT_OFCDC_SC_NM": "제주특별자치도교육청",
    "SD_SCHUL_CODE": "9296058",
    "SCHUL_NM": "외도초등학교"
  },
  {
    "ATPT_OFCDC_SC_CODE": "T10",
    "ATPT_OFCDC_SC_NM": "제주특별자치도교육청",
    "SD_SCHUL_CODE": "9296030",
    "SCHUL_NM": "우도중학교"
  },
  {
    "ATPT_OFCDC_SC_CODE": "T10",
    "ATPT_OFCDC_SC_NM": "제주특별자치도교육청",
    "SD_SCHUL_CODE": "9296095",
    "SCHUL_NM": "우도초등학교"
  },
  {
    "ATPT_OFCDC_SC_CODE": "T10",
    "ATPT_OFCDC_SC_NM": "제주특별자치도교육청",
    "SD_SCHUL_CODE": "9296064",
    "SCHUL_NM": "월랑초등학교"
  },
  {
    "ATPT_OFCDC_SC_CODE": "T10",
    "ATPT_OFCDC_SC_NM": "제주특별자치도교육청",
    "SD_SCHUL_CODE": "9299018",
    "SCHUL_NM": "위미중학교"
  },
  {
    "ATPT_OFCDC_SC_CODE": "T10",
    "ATPT_OFCDC_SC_NM": "제주특별자치도교육청",
    "SD_SCHUL_CODE": "9299055",
    "SCHUL_NM": "위미초등학교"
  },
  {
    "ATPT_OFCDC_SC_CODE": "T10",
    "ATPT_OFCDC_SC_NM": "제주특별자치도교육청",
    "SD_SCHUL_CODE": "9299053",
    "SCHUL_NM": "의귀초등학교"
  },
  {
    "ATPT_OFCDC_SC_CODE": "T10",
    "ATPT_OFCDC_SC_NM": "제주특별자치도교육청",
    "SD_SCHUL_CODE": "9296179",
    "SCHUL_NM": "이도초등학교"
  },
  {
    "ATPT_OFCDC_SC_CODE": "T10",
    "ATPT_OFCDC_SC_NM": "제주특별자치도교육청",
    "SD_SCHUL_CODE": "9296048",
    "SCHUL_NM": "인화초등학교"
  },
  {
    "ATPT_OFCDC_SC_CODE": "T10",
    "ATPT_OFCDC_SC_NM": "제주특별자치도교육청",
    "SD_SCHUL_CODE": "9296041",
    "SCHUL_NM": "일도초등학교"
  },
  {
    "ATPT_OFCDC_SC_CODE": "T10",
    "ATPT_OFCDC_SC_NM": "제주특별자치도교육청",
    "SD_SCHUL_CODE": "9296068",
    "SCHUL_NM": "장전초등학교"
  },
  {
    "ATPT_OFCDC_SC_CODE": "T10",
    "ATPT_OFCDC_SC_NM": "제주특별자치도교육청",
    "SD_SCHUL_CODE": "9296077",
    "SCHUL_NM": "재릉초등학교"
  },
  {
    "ATPT_OFCDC_SC_CODE": "T10",
    "ATPT_OFCDC_SC_NM": "제주특별자치도교육청",
    "SD_SCHUL_CODE": "9296024",
    "SCHUL_NM": "저청중학교"
  },
  {
    "ATPT_OFCDC_SC_CODE": "T10",
    "ATPT_OFCDC_SC_NM": "제주특별자치도교육청",
    "SD_SCHUL_CODE": "9296080",
    "SCHUL_NM": "저청초등학교"
  },
  {
    "ATPT_OFCDC_SC_CODE": "T10",
    "ATPT_OFCDC_SC_NM": "제주특별자치도교육청",
    "SD_SCHUL_CODE": "9290096",
    "SCHUL_NM": "제주고등학교"
  },
  {
    "ATPT_OFCDC_SC_CODE": "T10",
    "ATPT_OFCDC_SC_NM": "제주특별자치도교육청",
    "SD_SCHUL_CODE": "9290066",
    "SCHUL_NM": "제주과학고등학교"
  },
  {
    "ATPT_OFCDC_SC_CODE": "T10",
    "ATPT_OFCDC_SC_NM": "제주특별자치도교육청",
    "SD_SCHUL_CODE": "9296039",
    "SCHUL_NM": "제주남초등학교"
  },
  {
    "ATPT_OFCDC_SC_CODE": "T10",
    "ATPT_OFCDC_SC_NM": "제주특별자치도교육청",
    "SD_SCHUL_CODE": "C150029",
    "SCHUL_NM": "제주대학교교육대학부설초등학교"
  },
  {
    "ATPT_OFCDC_SC_CODE": "T10",
    "ATPT_OFCDC_SC_NM": "제주특별자치도교육청",
    "SD_SCHUL_CODE": "7003713",
    "SCHUL_NM": "제주대학교사범대학부설고등학교"
  },
  {
    "ATPT_OFCDC_SC_CODE": "T10",
    "ATPT_OFCDC_SC_NM": "제주특별자치도교육청",
    "SD_SCHUL_CODE": "7003714",
    "SCHUL_NM": "제주대학교사범대학부설중학교"
  },
  {
    "ATPT_OFCDC_SC_CODE": "T10",
    "ATPT_OFCDC_SC_NM": "제주특별자치도교육청",
    "SD_SCHUL_CODE": "9296014",
    "SCHUL_NM": "제주동여자중학교"
  },
  {
    "ATPT_OFCDC_SC_CODE": "T10",
    "ATPT_OFCDC_SC_NM": "제주특별자치도교육청",
    "SD_SCHUL_CODE": "9296015",
    "SCHUL_NM": "제주동중학교"
  },
  {
    "ATPT_OFCDC_SC_CODE": "T10",
    "ATPT_OFCDC_SC_NM": "제주특별자치도교육청",
    "SD_SCHUL_CODE": "9296037",
    "SCHUL_NM": "제주동초등학교"
  },
  {
    "ATPT_OFCDC_SC_CODE": "T10",
    "ATPT_OFCDC_SC_NM": "제주특별자치도교육청",
    "SD_SCHUL_CODE": "9296040",
    "SCHUL_NM": "제주북초등학교"
  },
  {
    "ATPT_OFCDC_SC_CODE": "T10",
    "ATPT_OFCDC_SC_NM": "제주특별자치도교육청",
    "SD_SCHUL_CODE": "9296016",
    "SCHUL_NM": "제주서중학교"
  },
  {
    "ATPT_OFCDC_SC_CODE": "T10",
    "ATPT_OFCDC_SC_NM": "제주특별자치도교육청",
    "SD_SCHUL_CODE": "9296038",
    "SCHUL_NM": "제주서초등학교"
  },
  {
    "ATPT_OFCDC_SC_CODE": "T10",
    "ATPT_OFCDC_SC_NM": "제주특별자치도교육청",
    "SD_SCHUL_CODE": "9290071",
    "SCHUL_NM": "제주여자고등학교"
  },
  {
    "ATPT_OFCDC_SC_CODE": "T10",
    "ATPT_OFCDC_SC_NM": "제주특별자치도교육청",
    "SD_SCHUL_CODE": "9290051",
    "SCHUL_NM": "제주여자상업고등학교"
  },
  {
    "ATPT_OFCDC_SC_CODE": "T10",
    "ATPT_OFCDC_SC_NM": "제주특별자치도교육청",
    "SD_SCHUL_CODE": "9296035",
    "SCHUL_NM": "제주여자중학교"
  },
  {
    "ATPT_OFCDC_SC_CODE": "T10",
    "ATPT_OFCDC_SC_NM": "제주특별자치도교육청",
    "SD_SCHUL_CODE": "9290084",
    "SCHUL_NM": "제주영송학교"
  },
  {
    "ATPT_OFCDC_SC_CODE": "T10",
    "ATPT_OFCDC_SC_NM": "제주특별자치도교육청",
    "SD_SCHUL_CODE": "9290083",
    "SCHUL_NM": "제주영지학교"
  },
  {
    "ATPT_OFCDC_SC_CODE": "T10",
    "ATPT_OFCDC_SC_NM": "제주특별자치도교육청",
    "SD_SCHUL_CODE": "9290204",
    "SCHUL_NM": "제주온라인학교"
  },
  {
    "ATPT_OFCDC_SC_CODE": "T10",
    "ATPT_OFCDC_SC_NM": "제주특별자치도교육청",
    "SD_SCHUL_CODE": "9290068",
    "SCHUL_NM": "제주외국어고등학교"
  },
  {
    "ATPT_OFCDC_SC_CODE": "T10",
    "ATPT_OFCDC_SC_NM": "제주특별자치도교육청",
    "SD_SCHUL_CODE": "9290049",
    "SCHUL_NM": "제주제일고등학교"
  },
  {
    "ATPT_OFCDC_SC_CODE": "T10",
    "ATPT_OFCDC_SC_NM": "제주특별자치도교육청",
    "SD_SCHUL_CODE": "9290079",
    "SCHUL_NM": "제주제일고등학교부설방송통신고등학교"
  },
  {
    "ATPT_OFCDC_SC_CODE": "T10",
    "ATPT_OFCDC_SC_NM": "제주특별자치도교육청",
    "SD_SCHUL_CODE": "9296011",
    "SCHUL_NM": "제주제일중학교"
  },
  {
    "ATPT_OFCDC_SC_CODE": "T10",
    "ATPT_OFCDC_SC_NM": "제주특별자치도교육청",
    "SD_SCHUL_CODE": "9296201",
    "SCHUL_NM": "제주제일중학교부설방송통신중학교"
  },
  {
    "ATPT_OFCDC_SC_CODE": "T10",
    "ATPT_OFCDC_SC_NM": "제주특별자치도교육청",
    "SD_SCHUL_CODE": "9290088",
    "SCHUL_NM": "제주중앙고등학교"
  },
  {
    "ATPT_OFCDC_SC_CODE": "T10",
    "ATPT_OFCDC_SC_NM": "제주특별자치도교육청",
    "SD_SCHUL_CODE": "9290050",
    "SCHUL_NM": "제주중앙여자고등학교"
  },
  {
    "ATPT_OFCDC_SC_CODE": "T10",
    "ATPT_OFCDC_SC_NM": "제주특별자치도교육청",
    "SD_SCHUL_CODE": "9296013",
    "SCHUL_NM": "제주중앙여자중학교"
  },
  {
    "ATPT_OFCDC_SC_CODE": "T10",
    "ATPT_OFCDC_SC_NM": "제주특별자치도교육청",
    "SD_SCHUL_CODE": "9296012",
    "SCHUL_NM": "제주중앙중학교"
  },
  {
    "ATPT_OFCDC_SC_CODE": "T10",
    "ATPT_OFCDC_SC_NM": "제주특별자치도교육청",
    "SD_SCHUL_CODE": "9296043",
    "SCHUL_NM": "제주중앙초등학교"
  },
  {
    "ATPT_OFCDC_SC_CODE": "T10",
    "ATPT_OFCDC_SC_NM": "제주특별자치도교육청",
    "SD_SCHUL_CODE": "9296033",
    "SCHUL_NM": "제주중학교"
  },
  {
    "ATPT_OFCDC_SC_CODE": "T10",
    "ATPT_OFCDC_SC_NM": "제주특별자치도교육청",
    "SD_SCHUL_CODE": "9296026",
    "SCHUL_NM": "조천중학교"
  },
  {
    "ATPT_OFCDC_SC_CODE": "T10",
    "ATPT_OFCDC_SC_NM": "제주특별자치도교육청",
    "SD_SCHUL_CODE": "9296083",
    "SCHUL_NM": "조천초등학교"
  },
  {
    "ATPT_OFCDC_SC_CODE": "T10",
    "ATPT_OFCDC_SC_NM": "제주특별자치도교육청",
    "SD_SCHUL_CODE": "9296101",
    "SCHUL_NM": "조천초등학교교래분교장"
  },
  {
    "ATPT_OFCDC_SC_CODE": "T10",
    "ATPT_OFCDC_SC_NM": "제주특별자치도교육청",
    "SD_SCHUL_CODE": "9296094",
    "SCHUL_NM": "종달초등학교"
  },
  {
    "ATPT_OFCDC_SC_CODE": "T10",
    "ATPT_OFCDC_SC_NM": "제주특별자치도교육청",
    "SD_SCHUL_CODE": "9290128",
    "SCHUL_NM": "중문고등학교"
  },
  {
    "ATPT_OFCDC_SC_CODE": "T10",
    "ATPT_OFCDC_SC_NM": "제주특별자치도교육청",
    "SD_SCHUL_CODE": "9299013",
    "SCHUL_NM": "중문중학교"
  },
  {
    "ATPT_OFCDC_SC_CODE": "T10",
    "ATPT_OFCDC_SC_NM": "제주특별자치도교육청",
    "SD_SCHUL_CODE": "9299033",
    "SCHUL_NM": "중문초등학교"
  },
  {
    "ATPT_OFCDC_SC_CODE": "T10",
    "ATPT_OFCDC_SC_NM": "제주특별자치도교육청",
    "SD_SCHUL_CODE": "9299066",
    "SCHUL_NM": "창천초등학교"
  },
  {
    "ATPT_OFCDC_SC_CODE": "T10",
    "ATPT_OFCDC_SC_NM": "제주특별자치도교육청",
    "SD_SCHUL_CODE": "9296031",
    "SCHUL_NM": "추자중학교"
  },
  {
    "ATPT_OFCDC_SC_CODE": "T10",
    "ATPT_OFCDC_SC_NM": "제주특별자치도교육청",
    "SD_SCHUL_CODE": "9296096",
    "SCHUL_NM": "추자초등학교"
  },
  {
    "ATPT_OFCDC_SC_CODE": "T10",
    "ATPT_OFCDC_SC_NM": "제주특별자치도교육청",
    "SD_SCHUL_CODE": "9296105",
    "SCHUL_NM": "추자초등학교신양분교장"
  },
  {
    "ATPT_OFCDC_SC_CODE": "T10",
    "ATPT_OFCDC_SC_NM": "제주특별자치도교육청",
    "SD_SCHUL_CODE": "9296174",
    "SCHUL_NM": "탐라중학교"
  },
  {
    "ATPT_OFCDC_SC_CODE": "T10",
    "ATPT_OFCDC_SC_NM": "제주특별자치도교육청",
    "SD_SCHUL_CODE": "9299052",
    "SCHUL_NM": "태흥초등학교"
  },
  {
    "ATPT_OFCDC_SC_CODE": "T10",
    "ATPT_OFCDC_SC_NM": "제주특별자치도교육청",
    "SD_SCHUL_CODE": "9299049",
    "SCHUL_NM": "토산초등학교"
  },
  {
    "ATPT_OFCDC_SC_CODE": "T10",
    "ATPT_OFCDC_SC_NM": "제주특별자치도교육청",
    "SD_SCHUL_CODE": "9299030",
    "SCHUL_NM": "토평초등학교"
  },
  {
    "ATPT_OFCDC_SC_CODE": "T10",
    "ATPT_OFCDC_SC_NM": "제주특별자치도교육청",
    "SD_SCHUL_CODE": "9296090",
    "SCHUL_NM": "평대초등학교"
  },
  {
    "ATPT_OFCDC_SC_CODE": "T10",
    "ATPT_OFCDC_SC_NM": "제주특별자치도교육청",
    "SD_SCHUL_CODE": "9290087",
    "SCHUL_NM": "표선고등학교"
  },
  {
    "ATPT_OFCDC_SC_CODE": "T10",
    "ATPT_OFCDC_SC_NM": "제주특별자치도교육청",
    "SD_SCHUL_CODE": "9299016",
    "SCHUL_NM": "표선중학교"
  },
  {
    "ATPT_OFCDC_SC_CODE": "T10",
    "ATPT_OFCDC_SC_NM": "제주특별자치도교육청",
    "SD_SCHUL_CODE": "9299046",
    "SCHUL_NM": "표선초등학교"
  },
  {
    "ATPT_OFCDC_SC_CODE": "T10",
    "ATPT_OFCDC_SC_NM": "제주특별자치도교육청",
    "SD_SCHUL_CODE": "9299045",
    "SCHUL_NM": "풍천초등학교"
  },
  {
    "ATPT_OFCDC_SC_CODE": "T10",
    "ATPT_OFCDC_SC_NM": "제주특별자치도교육청",
    "SD_SCHUL_CODE": "9296181",
    "SCHUL_NM": "하귀일초등학교"
  },
  {
    "ATPT_OFCDC_SC_CODE": "T10",
    "ATPT_OFCDC_SC_NM": "제주특별자치도교육청",
    "SD_SCHUL_CODE": "9296065",
    "SCHUL_NM": "하귀초등학교"
  },
  {
    "ATPT_OFCDC_SC_CODE": "T10",
    "ATPT_OFCDC_SC_NM": "제주특별자치도교육청",
    "SD_SCHUL_CODE": "9296093",
    "SCHUL_NM": "하도초등학교"
  },
  {
    "ATPT_OFCDC_SC_CODE": "T10",
    "ATPT_OFCDC_SC_NM": "제주특별자치도교육청",
    "SD_SCHUL_CODE": "9299057",
    "SCHUL_NM": "하례초등학교"
  },
  {
    "ATPT_OFCDC_SC_CODE": "T10",
    "ATPT_OFCDC_SC_NM": "제주특별자치도교육청",
    "SD_SCHUL_CODE": "9299036",
    "SCHUL_NM": "하원초등학교"
  },
  {
    "ATPT_OFCDC_SC_CODE": "T10",
    "ATPT_OFCDC_SC_NM": "제주특별자치도교육청",
    "SD_SCHUL_CODE": "9290104",
    "SCHUL_NM": "한국뷰티고등학교"
  },
  {
    "ATPT_OFCDC_SC_CODE": "T10",
    "ATPT_OFCDC_SC_NM": "제주특별자치도교육청",
    "SD_SCHUL_CODE": "9296089",
    "SCHUL_NM": "한동초등학교"
  },
  {
    "ATPT_OFCDC_SC_CODE": "T10",
    "ATPT_OFCDC_SC_NM": "제주특별자치도교육청",
    "SD_SCHUL_CODE": "9296018",
    "SCHUL_NM": "한라중학교"
  },
  {
    "ATPT_OFCDC_SC_CODE": "T10",
    "ATPT_OFCDC_SC_NM": "제주특별자치도교육청",
    "SD_SCHUL_CODE": "9296062",
    "SCHUL_NM": "한라초등학교"
  },
  {
    "ATPT_OFCDC_SC_CODE": "T10",
    "ATPT_OFCDC_SC_NM": "제주특별자치도교육청",
    "SD_SCHUL_CODE": "9290055",
    "SCHUL_NM": "한림고등학교"
  },
  {
    "ATPT_OFCDC_SC_CODE": "T10",
    "ATPT_OFCDC_SC_NM": "제주특별자치도교육청",
    "SD_SCHUL_CODE": "9290054",
    "SCHUL_NM": "한림공업고등학교"
  },
  {
    "ATPT_OFCDC_SC_CODE": "T10",
    "ATPT_OFCDC_SC_NM": "제주특별자치도교육청",
    "SD_SCHUL_CODE": "9296022",
    "SCHUL_NM": "한림여자중학교"
  },
  {
    "ATPT_OFCDC_SC_CODE": "T10",
    "ATPT_OFCDC_SC_NM": "제주특별자치도교육청",
    "SD_SCHUL_CODE": "9296021",
    "SCHUL_NM": "한림중학교"
  },
  {
    "ATPT_OFCDC_SC_CODE": "T10",
    "ATPT_OFCDC_SC_NM": "제주특별자치도교육청",
    "SD_SCHUL_CODE": "9296076",
    "SCHUL_NM": "한림초등학교"
  },
  {
    "ATPT_OFCDC_SC_CODE": "T10",
    "ATPT_OFCDC_SC_NM": "제주특별자치도교육청",
    "SD_SCHUL_CODE": "9296100",
    "SCHUL_NM": "한림초등학교비양분교장"
  },
  {
    "ATPT_OFCDC_SC_CODE": "T10",
    "ATPT_OFCDC_SC_NM": "제주특별자치도교육청",
    "SD_SCHUL_CODE": "9299050",
    "SCHUL_NM": "한마음초등학교"
  },
  {
    "ATPT_OFCDC_SC_CODE": "T10",
    "ATPT_OFCDC_SC_NM": "제주특별자치도교육청",
    "SD_SCHUL_CODE": "9296046",
    "SCHUL_NM": "한천초등학교"
  },
  {
    "ATPT_OFCDC_SC_CODE": "T10",
    "ATPT_OFCDC_SC_NM": "제주특별자치도교육청",
    "SD_SCHUL_CODE": "9290103",
    "SCHUL_NM": "함덕고등학교"
  },
  {
    "ATPT_OFCDC_SC_CODE": "T10",
    "ATPT_OFCDC_SC_NM": "제주특별자치도교육청",
    "SD_SCHUL_CODE": "9296027",
    "SCHUL_NM": "함덕중학교"
  },
  {
    "ATPT_OFCDC_SC_CODE": "T10",
    "ATPT_OFCDC_SC_NM": "제주특별자치도교육청",
    "SD_SCHUL_CODE": "9296085",
    "SCHUL_NM": "함덕초등학교"
  },
  {
    "ATPT_OFCDC_SC_CODE": "T10",
    "ATPT_OFCDC_SC_NM": "제주특별자치도교육청",
    "SD_SCHUL_CODE": "9296102",
    "SCHUL_NM": "함덕초등학교선인분교장"
  },
  {
    "ATPT_OFCDC_SC_CODE": "T10",
    "ATPT_OFCDC_SC_NM": "제주특별자치도교육청",
    "SD_SCHUL_CODE": "9296176",
    "SCHUL_NM": "해안초등학교"
  },
  {
    "ATPT_OFCDC_SC_CODE": "T10",
    "ATPT_OFCDC_SC_NM": "제주특별자치도교육청",
    "SD_SCHUL_CODE": "9296050",
    "SCHUL_NM": "화북초등학교"
  },
  {
    "ATPT_OFCDC_SC_CODE": "T10",
    "ATPT_OFCDC_SC_NM": "제주특별자치도교육청",
    "SD_SCHUL_CODE": "9299012",
    "SCHUL_NM": "효돈중학교"
  },
  {
    "ATPT_OFCDC_SC_CODE": "T10",
    "ATPT_OFCDC_SC_NM": "제주특별자치도교육청",
    "SD_SCHUL_CODE": "9299031",
    "SCHUL_NM": "효돈초등학교"
  },
  {
    "ATPT_OFCDC_SC_CODE": "T10",
    "ATPT_OFCDC_SC_NM": "제주특별자치도교육청",
    "SD_SCHUL_CODE": "9299051",
    "SCHUL_NM": "흥산초등학교"
  }
]